.gitignore
.travis.yml
MANIFEST.in
README.rst
qrz_example.py
settings_example.cfg
setup.py
tox.ini
pyQRZ.egg-info/PKG-INFO
pyQRZ.egg-info/SOURCES.txt
pyQRZ.egg-info/dependency_links.txt
pyQRZ.egg-info/requires.txt
pyQRZ.egg-info/top_level.txt
qrz/__init__.py
qrz/__init__.pyc
qrz/qrz_query.py
qrz/qrz_query.pyc
qrz/__pycache__/__init__.cpython-36.pyc
tests/__init__.py
tests/__init__.pyc
tests/test_qrz_query.py
tests/test_qrz_query.pyc
tests/__pycache__/__init__.cpython-36.pyc
tests/__pycache__/test_qrz_query.cpython-36.pyc